[
  {
    "name": "ボルメテウスコントロール",
    "description": "ボルメテウス・ホワイト・ドラゴンを勝ち筋に据えた光水火のコントロール。シールド焼却で盾回収を許さず、除去とカウンターで盤面を制圧しながらフィニッシュを狙う。",
    "civilization": [
      "光",
      "水",
      "火"
    ],
    "cards": [
      {
        "id": "dm06-s08",
        "name": "ボルメテウス・ホワイト・ドラゴン",
        "count": 1
      },
      {
        "id": "dm01-080",
        "name": "アクア・ハルカス",
        "count": 1
      },
      {
        "id": "dm01-052",
        "name": "サイバー・ブレイン",
        "count": 1
      },
      {
        "id": "dm05-024",
        "name": "アクア・サーファー",
        "count": 4
      },
      {
        "id": "dm01-015",
        "name": "ホーリー・スパーク",
        "count": 4
      },
      {
        "id": "dm01-086",
        "name": "スパイラル・ゲート",
        "count": 4
      },
      {
        "id": "dm02-040",
        "name": "コーライル",
        "count": 3
      }
    ],
    "tags": [
      "コントロール",
      "中速"
    ]
  },
  {
    "name": "天門（ヘブンズ・ゲートコントロール）",
    "description": "ヘブンズ・ゲートから大型ブロッカーを踏み倒す光主体のコントロール。聖霊王アルカディアスや聖鎧亜キング・アルカディアスで相手の行動を縛り、盤面を固めて勝つ。",
    "civilization": [
      "光",
      "闇"
    ],
    "cards": [
      {
        "id": "dm16-007",
        "name": "ヘブンズ・ゲート",
        "count": 4
      },
      {
        "id": "dm04-001",
        "name": "聖霊王アルカディアス",
        "count": 1
      },
      {
        "id": "dm26-s03",
        "name": "聖鎧亜キング・アルカディアス",
        "count": 2
      },
      {
        "id": "dm04-024",
        "name": "雷鳴の守護者ミスト・リエス",
        "count": 2
      },
      {
        "id": "dm01-015",
        "name": "ホーリー・スパーク",
        "count": 4
      },
      {
        "id": "dm05-024",
        "name": "アクア・サーファー",
        "count": 4
      }
    ],
    "tags": [
      "コントロール",
      "ビートダウン"
    ]
  },
  {
    "name": "サバキストライク",
    "description": "炎槍と水剣の裁（サバキ）や聖鎧亜クイーン・アルカディアスを軸にした光水火の中速ビート。除去と展開を両立し、テンポを握って押し切る。",
    "civilization": [
      "光",
      "水",
      "火"
    ],
    "cards": [
      {
        "id": "dm13-031",
        "name": "炎槍と水剣の裁",
        "count": 1
      },
      {
        "id": "dm27-005",
        "name": "聖鎧亜クイーン・アルカディアス",
        "count": 2
      },
      {
        "id": "dm01-080",
        "name": "アクア・ハルカス",
        "count": 4
      },
      {
        "id": "dm09-017",
        "name": "サウザンド・スピア",
        "count": 3
      },
      {
        "id": "dm05-024",
        "name": "アクア・サーファー",
        "count": 4
      },
      {
        "id": "dm01-015",
        "name": "ホーリー・スパーク",
        "count": 4
      }
    ],
    "tags": [
      "ビートダウン",
      "中速"
    ]
  },
  {
    "name": "除去サファイア（火単速攻〜中速）",
    "description": "クリスタル・ランサーやボルメテウス・武者・ドラゴンを絡めた攻撃的な構築。除去呪文で相手の盤面を捌きつつ、ドラゴンで一気に詰める。",
    "civilization": [
      "水",
      "火"
    ],
    "cards": [
      {
        "id": "dm02-024",
        "name": "クリスタル・ランサー",
        "count": 4
      },
      {
        "id": "dm24-s04",
        "name": "ボルメテウス・武者・ドラゴン",
        "count": 2
      },
      {
        "id": "dm01-052",
        "name": "サイバー・ブレイン",
        "count": 1
      },
      {
        "id": "dm05-024",
        "name": "アクア・サーファー",
        "count": 4
      },
      {
        "id": "dm01-086",
        "name": "スパイラル・ゲート",
        "count": 3
      }
    ],
    "tags": [
      "ビートダウン",
      "中速"
    ]
  },
  {
    "name": "ネクラコントロール",
    "description": "光闇自然（ネクラ）のマナ加速からインフェルノ・ゲートや魔刻の斬将オルゼキアで盤面を崩し、大型クリーチャーでコントロールするデッキ。",
    "civilization": [
      "光",
      "闇",
      "自然"
    ],
    "cards": [
      {
        "id": "dm06-110",
        "name": "フェアリー・ライフ",
        "count": 4
      },
      {
        "id": "dm01-106",
        "name": "青銅の鎧",
        "count": 4
      },
      {
        "id": "dm10-036",
        "name": "母なる大地",
        "count": 1
      },
      {
        "id": "dm19-027",
        "name": "インフェルノ・ゲート",
        "count": 1
      },
      {
        "id": "dm25-s01",
        "name": "魔刻の斬将オルゼキア",
        "count": 2
      },
      {
        "id": "dm01-027",
        "name": "デーモン・ハンド",
        "count": 4
      },
      {
        "id": "dm02-029",
        "name": "ロスト・ソウル",
        "count": 3
      },
      {
        "id": "dm08-s04",
        "name": "超竜バジュラ",
        "count": 1
      }
    ],
    "tags": [
      "コントロール",
      "低速"
    ]
  }
]